justunzip/__init__.py
justunzip/justunzip.py
justunzip-0.0.11.dist-info/LICENSE
justunzip-0.0.11.dist-info/METADATA
justunzip-0.0.11.dist-info/WHEEL
justunzip-0.0.11.dist-info/entry_points.txt
justunzip-0.0.11.dist-info/top_level.txt
justunzip-0.0.11.dist-info/RECORD
