Metadata-Version: 2.1
Name: justunzip
Version: 0.0.11
Summary: unzip truncated or corrupt zip files
Home-page: https://github.com/vwood/justunzip
Download-URL: https://github.com/vwood/justunzip/archive/refs/tags/v0.0.11.tar.gz
Author: vwood
Author-email: vwood@vwood.org
License: MIT
Keywords: zip truncated corrupt zipfile archive unzip
Platform: UNKNOWN
Classifier: Programming Language :: Python :: 3
Classifier: License :: OSI Approved :: MIT License
Classifier: Operating System :: OS Independent
Classifier: Environment :: Console
Classifier: Topic :: System :: Archiving :: Compression
Classifier: Topic :: Utilities
Requires-Python: >=3.6
License-File: LICENSE
Requires-Dist: click (>=7.1)
